rdt/transformers/addons/identity/__init__.py
rdt/transformers/addons/identity/identity.py
rdt_identity.egg-info/PKG-INFO
rdt_identity.egg-info/SOURCES.txt
rdt_identity.egg-info/dependency_links.txt
rdt_identity.egg-info/not-zip-safe
rdt_identity.egg-info/requires.txt
rdt_identity.egg-info/top_level.txt
rdt_identity-1.9.2.dist-info/AUTHORS.rst
rdt_identity-1.9.2.dist-info/LICENSE
rdt_identity-1.9.2.dist-info/METADATA
rdt_identity-1.9.2.dist-info/WHEEL
rdt_identity-1.9.2.dist-info/top_level.txt
rdt_identity-1.9.2.dist-info/RECORD
