Metadata-Version: 2.1
Name: rdt-identity
Version: 1.9.2
Summary: Reversible Data Transforms
Home-page: https://github.com/sdv-dev/RDT
Author: DataCebo, Inc.
Author-email: info@sdv.dev
License: BSL-1.1
Keywords: rdt,rdt_identity
Classifier: Development Status :: 2 - Pre-Alpha
Classifier: Intended Audience :: Developers
Classifier: License :: Free for non-commercial use
Classifier: Natural Language :: English
Classifier: Programming Language :: Python :: 3
Classifier: Programming Language :: Python :: 3.8
Classifier: Programming Language :: Python :: 3.9
Classifier: Programming Language :: Python :: 3.10
Classifier: Programming Language :: Python :: 3.11
Classifier: Topic :: Scientific/Engineering :: Artificial Intelligence
Requires-Python: >=3.8,<3.12
License-File: LICENSE
License-File: AUTHORS.rst
Requires-Dist: rdt >=1.9.2
